{
    "id": 2,
    "method": "stage_2",
    "content": {
        "arguments": {
            "vesPostion": {
                "a1": {
                    "coord": [
                        121.67855451807533,
                        38.83094151781192
                    ],
                    "spd": 9.000076976907517,
                    "course": 302.4717112156935
                },
                "a2": {
                    "coord": [
                        121.6739476849719,
                        38.82385463860221
                    ],
                    "spd": 9.000076976907517,
                    "course": 302.4717112156935
                },
                "a3": {
                    "coord": [
                        121.66833597200328,
                        38.81894039935956
                    ],
                    "spd": 9.000076976907517,
                    "course": 302.4717112156935
                },
                "a4": {
                    "coord": [
                        121.66852122059436,
                        38.81937722131918
                    ],
                    "spd": 9.000076976907517,
                    "course": 302.4717112156935
                },
                "a5": {
                    "coord": [
                        121.66733644468772,
                        38.815989966603816
                    ],
                    "spd": 9.000076976907517,
                    "course": 302.4717112156935
                },
                "a6": {
                    "coord": [
                        121.663678954749,
                        38.806960290130384
                    ],
                    "spd": 9.000076976907517,
                    "course": 302.4717112156935
                },
                "a7": {
                    "coord": [
                        121.66588858313314,
                        38.80576951480442
                    ],
                    "spd": 9.000076976907517,
                    "course": 302.4717112156935
                },
                "a8": {
                    "coord": [
                        121.67020244838854,
                        38.801688748941764
                    ],
                    "spd": 9.000076976907517,
                    "course": 302.4717112156935
                }
            },
            "road": [
                {
                    "id": "a1",
                    "path": {
                        "shape": "LineString",
                        "points": [
                            {
                                "coord": [
                                    121.67891009395845,
                                    38.83094042991706
                                ],
                                "spd": 20.000171059794
                            }
                        ]
                    }
                },
                {
                    "id": "a2",
                    "path": {
                        "shape": "LineString",
                        "points": [
                            {
                                "coord": [
                                    121.67381191675527,
                                    38.82381314643138
                                ],
                                "spd": 9.000076976906664
                            }
                        ]
                    }
                },
                {
                    "id": "a3",
                    "path": {
                        "shape": "LineString",
                        "points": [
                            {
                                "coord": [
                                    121.66863165261536,
                                    38.81884367173623
                                ],
                                "spd": 20.000171059792585
                            }
                        ]
                    }
                },
                {
                    "id": "a4",
                    "path": {
                        "shape": "LineString",
                        "points": [
                            {
                                "coord": [
                                    121.66887188772043,
                                    38.819405680981276
                                ],
                                "spd": 20.00017105979371
                            }
                        ]
                    }
                },
                {
                    "id": "a5",
                    "path": {
                        "shape": "LineString",
                        "points": [
                            {
                                "coord": [
                                    121.66740975604486,
                                    38.81592026493065
                                ],
                                "spd": 9.000076976907174
                            }
                        ]
                    }
                },
                {
                    "id": "a6",
                    "path": {
                        "shape": "LineString",
                        "points": [
                            {
                                "coord": [
                                    121.663678954749,
                                    38.806960290130384
                                ],
                                "spd": 20.000171059792958
                            }
                        ]
                    }
                },
                {
                    "id": "a7",
                    "path": {
                        "shape": "LineString",
                        "points": [
                            {
                                "coord": [
                                    121.6661363607347,
                                    38.80589435800339
                                ],
                                "spd": 20.000171059793043
                            }
                        ]
                    }
                },
                {
                    "id": "a8",
                    "path": {
                        "shape": "LineString",
                        "points": [
                            {
                                "coord": [
                                    121.67027216392128,
                                    38.80161821767412
                                ],
                                "spd": 9.000076976907517
                            }
                        ]
                    }
                },
                {
                    "id": "a1",
                    "path": {
                        "shape": "LineString",
                        "points": [
                            {
                                "coord": [
                                    121.67891009395845,
                                    38.83094042991706
                                ],
                                "spd": 20.000171059794
                            }
                        ]
                    }
                },
                {
                    "id": "a2",
                    "path": {
                        "shape": "LineString",
                        "points": [
                            {
                                "coord": [
                                    121.67381191675527,
                                    38.82381314643138
                                ],
                                "spd": 9.000076976906664
                            }
                        ]
                    }
                },
                {
                    "id": "a3",
                    "path": {
                        "shape": "LineString",
                        "points": [
                            {
                                "coord": [
                                    121.66863165261536,
                                    38.81884367173623
                                ],
                                "spd": 20.000171059792585
                            }
                        ]
                    }
                },
                {
                    "id": "a4",
                    "path": {
                        "shape": "LineString",
                        "points": [
                            {
                                "coord": [
                                    121.66887188772043,
                                    38.819405680981276
                                ],
                                "spd": 20.00017105979371
                            }
                        ]
                    }
                },
                {
                    "id": "a5",
                    "path": {
                        "shape": "LineString",
                        "points": [
                            {
                                "coord": [
                                    121.66740975604486,
                                    38.81592026493065
                                ],
                                "spd": 9.000076976907174
                            }
                        ]
                    }
                },
                {
                    "id": "a6",
                    "path": {
                        "shape": "LineString",
                        "points": [
                            {
                                "coord": [
                                    121.663678954749,
                                    38.806960290130384
                                ],
                                "spd": 20.000171059792958
                            }
                        ]
                    }
                },
                {
                    "id": "a7",
                    "path": {
                        "shape": "LineString",
                        "points": [
                            {
                                "coord": [
                                    121.6661363607347,
                                    38.80589435800339
                                ],
                                "spd": 20.000171059793043
                            }
                        ]
                    }
                },
                {
                    "id": "a8",
                    "path": {
                        "shape": "LineString",
                        "points": [
                            {
                                "coord": [
                                    121.67027216392128,
                                    38.80161821767412
                                ],
                                "spd": 9.000076976907517
                            }
                        ]
                    }
                },
                {
                    "id": "a1",
                    "path": {
                        "shape": "LineString",
                        "points": [
                            {
                                "coord": [
                                    121.67891009395845,
                                    38.83094042991706
                                ],
                                "spd": 20.000171059794
                            }
                        ]
                    }
                },
                {
                    "id": "a2",
                    "path": {
                        "shape": "LineString",
                        "points": [
                            {
                                "coord": [
                                    121.67381191675527,
                                    38.82381314643138
                                ],
                                "spd": 9.000076976906664
                            }
                        ]
                    }
                },
                {
                    "id": "a3",
                    "path": {
                        "shape": "LineString",
                        "points": [
                            {
                                "coord": [
                                    121.66863165261536,
                                    38.81884367173623
                                ],
                                "spd": 20.000171059792585
                            }
                        ]
                    }
                },
                {
                    "id": "a4",
                    "path": {
                        "shape": "LineString",
                        "points": [
                            {
                                "coord": [
                                    121.66887188772043,
                                    38.819405680981276
                                ],
                                "spd": 20.00017105979371
                            }
                        ]
                    }
                },
                {
                    "id": "a5",
                    "path": {
                        "shape": "LineString",
                        "points": [
                            {
                                "coord": [
                                    121.66740975604486,
                                    38.81592026493065
                                ],
                                "spd": 9.000076976907174
                            }
                        ]
                    }
                },
                {
                    "id": "a6",
                    "path": {
                        "shape": "LineString",
                        "points": [
                            {
                                "coord": [
                                    121.663678954749,
                                    38.806960290130384
                                ],
                                "spd": 20.000171059792958
                            }
                        ]
                    }
                },
                {
                    "id": "a7",
                    "path": {
                        "shape": "LineString",
                        "points": [
                            {
                                "coord": [
                                    121.6661363607347,
                                    38.80589435800339
                                ],
                                "spd": 20.000171059793043
                            }
                        ]
                    }
                },
                {
                    "id": "a8",
                    "path": {
                        "shape": "LineString",
                        "points": [
                            {
                                "coord": [
                                    121.67027216392128,
                                    38.80161821767412
                                ],
                                "spd": 9.000076976907517
                            }
                        ]
                    }
                },
                {
                    "id": "a1",
                    "path": {
                        "shape": "LineString",
                        "points": [
                            {
                                "coord": [
                                    121.67891009395845,
                                    38.83094042991706
                                ],
                                "spd": 20.000171059794
                            }
                        ]
                    }
                },
                {
                    "id": "a2",
                    "path": {
                        "shape": "LineString",
                        "points": [
                            {
                                "coord": [
                                    121.67381191675527,
                                    38.82381314643138
                                ],
                                "spd": 9.000076976906664
                            }
                        ]
                    }
                },
                {
                    "id": "a3",
                    "path": {
                        "shape": "LineString",
                        "points": [
                            {
                                "coord": [
                                    121.66863165261536,
                                    38.81884367173623
                                ],
                                "spd": 20.000171059792585
                            }
                        ]
                    }
                },
                {
                    "id": "a4",
                    "path": {
                        "shape": "LineString",
                        "points": [
                            {
                                "coord": [
                                    121.66887188772043,
                                    38.819405680981276
                                ],
                                "spd": 20.00017105979371
                            }
                        ]
                    }
                },
                {
                    "id": "a5",
                    "path": {
                        "shape": "LineString",
                        "points": [
                            {
                                "coord": [
                                    121.66740975604486,
                                    38.81592026493065
                                ],
                                "spd": 9.000076976907174
                            }
                        ]
                    }
                },
                {
                    "id": "a6",
                    "path": {
                        "shape": "LineString",
                        "points": [
                            {
                                "coord": [
                                    121.663678954749,
                                    38.806960290130384
                                ],
                                "spd": 20.000171059792958
                            }
                        ]
                    }
                },
                {
                    "id": "a7",
                    "path": {
                        "shape": "LineString",
                        "points": [
                            {
                                "coord": [
                                    121.6661363607347,
                                    38.80589435800339
                                ],
                                "spd": 20.000171059793043
                            }
                        ]
                    }
                },
                {
                    "id": "a8",
                    "path": {
                        "shape": "LineString",
                        "points": [
                            {
                                "coord": [
                                    121.67027216392128,
                                    38.80161821767412
                                ],
                                "spd": 9.000076976907517
                            }
                        ]
                    }
                },
                {
                    "id": "a1",
                    "path": {
                        "shape": "LineString",
                        "points": [
                            {
                                "coord": [
                                    121.67891009395845,
                                    38.83094042991706
                                ],
                                "spd": 20.000171059794
                            }
                        ]
                    }
                },
                {
                    "id": "a2",
                    "path": {
                        "shape": "LineString",
                        "points": [
                            {
                                "coord": [
                                    121.67381191675527,
                                    38.82381314643138
                                ],
                                "spd": 9.000076976906664
                            }
                        ]
                    }
                },
                {
                    "id": "a3",
                    "path": {
                        "shape": "LineString",
                        "points": [
                            {
                                "coord": [
                                    121.66863165261536,
                                    38.81884367173623
                                ],
                                "spd": 20.000171059792585
                            }
                        ]
                    }
                },
                {
                    "id": "a4",
                    "path": {
                        "shape": "LineString",
                        "points": [
                            {
                                "coord": [
                                    121.66887188772043,
                                    38.819405680981276
                                ],
                                "spd": 20.00017105979371
                            }
                        ]
                    }
                },
                {
                    "id": "a5",
                    "path": {
                        "shape": "LineString",
                        "points": [
                            {
                                "coord": [
                                    121.66740975604486,
                                    38.81592026493065
                                ],
                                "spd": 9.000076976907174
                            }
                        ]
                    }
                },
                {
                    "id": "a6",
                    "path": {
                        "shape": "LineString",
                        "points": [
                            {
                                "coord": [
                                    121.663678954749,
                                    38.806960290130384
                                ],
                                "spd": 20.000171059792958
                            }
                        ]
                    }
                },
                {
                    "id": "a7",
                    "path": {
                        "shape": "LineString",
                        "points": [
                            {
                                "coord": [
                                    121.6661363607347,
                                    38.80589435800339
                                ],
                                "spd": 20.000171059793043
                            }
                        ]
                    }
                },
                {
                    "id": "a8",
                    "path": {
                        "shape": "LineString",
                        "points": [
                            {
                                "coord": [
                                    121.67027216392128,
                                    38.80161821767412
                                ],
                                "spd": 9.000076976907517
                            }
                        ]
                    }
                },
                {
                    "id": "a1",
                    "path": {
                        "shape": "LineString",
                        "points": [
                            {
                                "coord": [
                                    121.67891009395845,
                                    38.83094042991706
                                ],
                                "spd": 20.000171059794
                            }
                        ]
                    }
                },
                {
                    "id": "a2",
                    "path": {
                        "shape": "LineString",
                        "points": [
                            {
                                "coord": [
                                    121.67381191675527,
                                    38.82381314643138
                                ],
                                "spd": 9.000076976906664
                            }
                        ]
                    }
                },
                {
                    "id": "a3",
                    "path": {
                        "shape": "LineString",
                        "points": [
                            {
                                "coord": [
                                    121.66863165261536,
                                    38.81884367173623
                                ],
                                "spd": 20.000171059792585
                            }
                        ]
                    }
                },
                {
                    "id": "a4",
                    "path": {
                        "shape": "LineString",
                        "points": [
                            {
                                "coord": [
                                    121.66887188772043,
                                    38.819405680981276
                                ],
                                "spd": 20.00017105979371
                            }
                        ]
                    }
                },
                {
                    "id": "a5",
                    "path": {
                        "shape": "LineString",
                        "points": [
                            {
                                "coord": [
                                    121.66740975604486,
                                    38.81592026493065
                                ],
                                "spd": 9.000076976907174
                            }
                        ]
                    }
                },
                {
                    "id": "a6",
                    "path": {
                        "shape": "LineString",
                        "points": [
                            {
                                "coord": [
                                    121.663678954749,
                                    38.806960290130384
                                ],
                                "spd": 20.000171059792958
                            }
                        ]
                    }
                },
                {
                    "id": "a7",
                    "path": {
                        "shape": "LineString",
                        "points": [
                            {
                                "coord": [
                                    121.6661363607347,
                                    38.80589435800339
                                ],
                                "spd": 20.000171059793043
                            }
                        ]
                    }
                },
                {
                    "id": "a8",
                    "path": {
                        "shape": "LineString",
                        "points": [
                            {
                                "coord": [
                                    121.67027216392128,
                                    38.80161821767412
                                ],
                                "spd": 9.000076976907517
                            }
                        ]
                    }
                },
                {
                    "id": "a1",
                    "path": {
                        "shape": "LineString",
                        "points": [
                            {
                                "coord": [
                                    121.67891009395845,
                                    38.83094042991706
                                ],
                                "spd": 20.000171059794
                            }
                        ]
                    }
                },
                {
                    "id": "a2",
                    "path": {
                        "shape": "LineString",
                        "points": [
                            {
                                "coord": [
                                    121.67381191675527,
                                    38.82381314643138
                                ],
                                "spd": 9.000076976906664
                            }
                        ]
                    }
                },
                {
                    "id": "a3",
                    "path": {
                        "shape": "LineString",
                        "points": [
                            {
                                "coord": [
                                    121.66863165261536,
                                    38.81884367173623
                                ],
                                "spd": 20.000171059792585
                            }
                        ]
                    }
                },
                {
                    "id": "a4",
                    "path": {
                        "shape": "LineString",
                        "points": [
                            {
                                "coord": [
                                    121.66887188772043,
                                    38.819405680981276
                                ],
                                "spd": 20.00017105979371
                            }
                        ]
                    }
                },
                {
                    "id": "a5",
                    "path": {
                        "shape": "LineString",
                        "points": [
                            {
                                "coord": [
                                    121.66740975604486,
                                    38.81592026493065
                                ],
                                "spd": 9.000076976907174
                            }
                        ]
                    }
                },
                {
                    "id": "a6",
                    "path": {
                        "shape": "LineString",
                        "points": [
                            {
                                "coord": [
                                    121.663678954749,
                                    38.806960290130384
                                ],
                                "spd": 20.000171059792958
                            }
                        ]
                    }
                },
                {
                    "id": "a7",
                    "path": {
                        "shape": "LineString",
                        "points": [
                            {
                                "coord": [
                                    121.6661363607347,
                                    38.80589435800339
                                ],
                                "spd": 20.000171059793043
                            }
                        ]
                    }
                },
                {
                    "id": "a8",
                    "path": {
                        "shape": "LineString",
                        "points": [
                            {
                                "coord": [
                                    121.67027216392128,
                                    38.80161821767412
                                ],
                                "spd": 9.000076976907517
                            }
                        ]
                    }
                },
                {
                    "id": "a1",
                    "path": {
                        "shape": "LineString",
                        "points": [
                            {
                                "coord": [
                                    121.67891009395845,
                                    38.83094042991706
                                ],
                                "spd": 20.000171059794
                            }
                        ]
                    }
                },
                {
                    "id": "a2",
                    "path": {
                        "shape": "LineString",
                        "points": [
                            {
                                "coord": [
                                    121.67381191675527,
                                    38.82381314643138
                                ],
                                "spd": 9.000076976906664
                            }
                        ]
                    }
                },
                {
                    "id": "a3",
                    "path": {
                        "shape": "LineString",
                        "points": [
                            {
                                "coord": [
                                    121.66863165261536,
                                    38.81884367173623
                                ],
                                "spd": 20.000171059792585
                            }
                        ]
                    }
                },
                {
                    "id": "a4",
                    "path": {
                        "shape": "LineString",
                        "points": [
                            {
                                "coord": [
                                    121.66887188772043,
                                    38.819405680981276
                                ],
                                "spd": 20.00017105979371
                            }
                        ]
                    }
                },
                {
                    "id": "a5",
                    "path": {
                        "shape": "LineString",
                        "points": [
                            {
                                "coord": [
                                    121.66740975604486,
                                    38.81592026493065
                                ],
                                "spd": 9.000076976907174
                            }
                        ]
                    }
                },
                {
                    "id": "a6",
                    "path": {
                        "shape": "LineString",
                        "points": [
                            {
                                "coord": [
                                    121.663678954749,
                                    38.806960290130384
                                ],
                                "spd": 20.000171059792958
                            }
                        ]
                    }
                },
                {
                    "id": "a7",
                    "path": {
                        "shape": "LineString",
                        "points": [
                            {
                                "coord": [
                                    121.6661363607347,
                                    38.80589435800339
                                ],
                                "spd": 20.000171059793043
                            }
                        ]
                    }
                },
                {
                    "id": "a8",
                    "path": {
                        "shape": "LineString",
                        "points": [
                            {
                                "coord": [
                                    121.67027216392128,
                                    38.80161821767412
                                ],
                                "spd": 9.000076976907517
                            }
                        ]
                    }
                }
            ]
        }
    }
}