{
    "id": 2,
    "method": "stage_2",
    "content": {
        "arguments": {
            "vesPostion": {
                "a1": {
                    "coord": [
                        121.68724965007729,
                        38.82845100074398
                    ],
                    "spd": 20.000171059792958,
                    "course": 141.14758327999238
                },
                "a2": {
                    "coord": [
                        121.68723313128756,
                        38.82403513498484
                    ],
                    "spd": 20.000171059792958,
                    "course": 141.14758327999238
                },
                "a3": {
                    "coord": [
                        121.68779113221521,
                        38.817223810212504
                    ],
                    "spd": 20.000171059792958,
                    "course": 141.14758327999238
                },
                "a4": {
                    "coord": [
                        121.68445342169512,
                        38.8215295668298
                    ],
                    "spd": 20.000171059792958,
                    "course": 141.14758327999238
                },
                "a5": {
                    "coord": [
                        121.68593324846263,
                        38.81453810118285
                    ],
                    "spd": 20.000171059792958,
                    "course": 141.14758327999238
                },
                "a6": {
                    "coord": [
                        121.67964748255426,
                        38.81112943902595
                    ],
                    "spd": 20.000171059792958,
                    "course": 141.14758327999238
                },
                "a7": {
                    "coord": [
                        121.67178434113204,
                        38.80940044842448
                    ],
                    "spd": 20.000171059792958,
                    "course": 141.14758327999238
                },
                "a8": {
                    "coord": [
                        121.68268689901409,
                        38.803436638071965
                    ],
                    "spd": 20.000171059792958,
                    "course": 141.14758327999238
                }
            },
            "road": [
                {
                    "id": "a1",
                    "path": {
                        "shape": "LineString",
                        "points": [
                            {
                                "coord": [
                                    121.68737506505946,
                                    38.82849972627012
                                ],
                                "spd": 9.000076976907332
                            }
                        ]
                    }
                },
                {
                    "id": "a2",
                    "path": {
                        "shape": "LineString",
                        "points": [
                            {
                                "coord": [
                                    121.68713695744593,
                                    38.82397244143634
                                ],
                                "spd": 9.000076976906529
                            }
                        ]
                    }
                },
                {
                    "id": "a3",
                    "path": {
                        "shape": "LineString",
                        "points": [
                            {
                                "coord": [
                                    121.68814169761252,
                                    38.817252488164584
                                ],
                                "spd": 20.000171059793427
                            }
                        ]
                    }
                },
                {
                    "id": "a4",
                    "path": {
                        "shape": "LineString",
                        "points": [
                            {
                                "coord": [
                                    121.68479163708531,
                                    38.82158321082087
                                ],
                                "spd": 20.00017105979263
                            }
                        ]
                    }
                },
                {
                    "id": "a5",
                    "path": {
                        "shape": "LineString",
                        "points": [
                            {
                                "coord": [
                                    121.68608278233754,
                                    38.81451030153296
                                ],
                                "spd": 9.000076976906637
                            }
                        ]
                    }
                },
                {
                    "id": "a6",
                    "path": {
                        "shape": "LineString",
                        "points": [
                            {
                                "coord": [
                                    121.67967689957855,
                                    38.81105236664077
                                ],
                                "spd": 9.000076976907105
                            }
                        ]
                    }
                },
                {
                    "id": "a7",
                    "path": {
                        "shape": "LineString",
                        "points": [
                            {
                                "coord": [
                                    121.6717353559328,
                                    38.80944687210242
                                ],
                                "spd": 0.0
                            }
                        ]
                    }
                },
                {
                    "id": "a8",
                    "path": {
                        "shape": "LineString",
                        "points": [
                            {
                                "coord": [
                                    121.68264256220472,
                                    38.803609465137754
                                ],
                                "spd": 20.000171059792958
                            }
                        ]
                    }
                },
                {
                    "id": "a1",
                    "path": {
                        "shape": "LineString",
                        "points": [
                            {
                                "coord": [
                                    121.68737506505946,
                                    38.82849972627012
                                ],
                                "spd": 9.000076976907332
                            }
                        ]
                    }
                },
                {
                    "id": "a2",
                    "path": {
                        "shape": "LineString",
                        "points": [
                            {
                                "coord": [
                                    121.68713695744593,
                                    38.82397244143634
                                ],
                                "spd": 9.000076976906529
                            }
                        ]
                    }
                },
                {
                    "id": "a3",
                    "path": {
                        "shape": "LineString",
                        "points": [
                            {
                                "coord": [
                                    121.68814169761252,
                                    38.817252488164584
                                ],
                                "spd": 20.000171059793427
                            }
                        ]
                    }
                },
                {
                    "id": "a4",
                    "path": {
                        "shape": "LineString",
                        "points": [
                            {
                                "coord": [
                                    121.68479163708531,
                                    38.82158321082087
                                ],
                                "spd": 20.00017105979263
                            }
                        ]
                    }
                },
                {
                    "id": "a5",
                    "path": {
                        "shape": "LineString",
                        "points": [
                            {
                                "coord": [
                                    121.68608278233754,
                                    38.81451030153296
                                ],
                                "spd": 9.000076976906637
                            }
                        ]
                    }
                },
                {
                    "id": "a6",
                    "path": {
                        "shape": "LineString",
                        "points": [
                            {
                                "coord": [
                                    121.67967689957855,
                                    38.81105236664077
                                ],
                                "spd": 9.000076976907105
                            }
                        ]
                    }
                },
                {
                    "id": "a7",
                    "path": {
                        "shape": "LineString",
                        "points": [
                            {
                                "coord": [
                                    121.6717353559328,
                                    38.80944687210242
                                ],
                                "spd": 0.0
                            }
                        ]
                    }
                },
                {
                    "id": "a8",
                    "path": {
                        "shape": "LineString",
                        "points": [
                            {
                                "coord": [
                                    121.68264256220472,
                                    38.803609465137754
                                ],
                                "spd": 20.000171059792958
                            }
                        ]
                    }
                },
                {
                    "id": "a1",
                    "path": {
                        "shape": "LineString",
                        "points": [
                            {
                                "coord": [
                                    121.68737506505946,
                                    38.82849972627012
                                ],
                                "spd": 9.000076976907332
                            }
                        ]
                    }
                },
                {
                    "id": "a2",
                    "path": {
                        "shape": "LineString",
                        "points": [
                            {
                                "coord": [
                                    121.68713695744593,
                                    38.82397244143634
                                ],
                                "spd": 9.000076976906529
                            }
                        ]
                    }
                },
                {
                    "id": "a3",
                    "path": {
                        "shape": "LineString",
                        "points": [
                            {
                                "coord": [
                                    121.68814169761252,
                                    38.817252488164584
                                ],
                                "spd": 20.000171059793427
                            }
                        ]
                    }
                },
                {
                    "id": "a4",
                    "path": {
                        "shape": "LineString",
                        "points": [
                            {
                                "coord": [
                                    121.68479163708531,
                                    38.82158321082087
                                ],
                                "spd": 20.00017105979263
                            }
                        ]
                    }
                },
                {
                    "id": "a5",
                    "path": {
                        "shape": "LineString",
                        "points": [
                            {
                                "coord": [
                                    121.68608278233754,
                                    38.81451030153296
                                ],
                                "spd": 9.000076976906637
                            }
                        ]
                    }
                },
                {
                    "id": "a6",
                    "path": {
                        "shape": "LineString",
                        "points": [
                            {
                                "coord": [
                                    121.67967689957855,
                                    38.81105236664077
                                ],
                                "spd": 9.000076976907105
                            }
                        ]
                    }
                },
                {
                    "id": "a7",
                    "path": {
                        "shape": "LineString",
                        "points": [
                            {
                                "coord": [
                                    121.6717353559328,
                                    38.80944687210242
                                ],
                                "spd": 0.0
                            }
                        ]
                    }
                },
                {
                    "id": "a8",
                    "path": {
                        "shape": "LineString",
                        "points": [
                            {
                                "coord": [
                                    121.68264256220472,
                                    38.803609465137754
                                ],
                                "spd": 20.000171059792958
                            }
                        ]
                    }
                },
                {
                    "id": "a1",
                    "path": {
                        "shape": "LineString",
                        "points": [
                            {
                                "coord": [
                                    121.68737506505946,
                                    38.82849972627012
                                ],
                                "spd": 9.000076976907332
                            }
                        ]
                    }
                },
                {
                    "id": "a2",
                    "path": {
                        "shape": "LineString",
                        "points": [
                            {
                                "coord": [
                                    121.68713695744593,
                                    38.82397244143634
                                ],
                                "spd": 9.000076976906529
                            }
                        ]
                    }
                },
                {
                    "id": "a3",
                    "path": {
                        "shape": "LineString",
                        "points": [
                            {
                                "coord": [
                                    121.68814169761252,
                                    38.817252488164584
                                ],
                                "spd": 20.000171059793427
                            }
                        ]
                    }
                },
                {
                    "id": "a4",
                    "path": {
                        "shape": "LineString",
                        "points": [
                            {
                                "coord": [
                                    121.68479163708531,
                                    38.82158321082087
                                ],
                                "spd": 20.00017105979263
                            }
                        ]
                    }
                },
                {
                    "id": "a5",
                    "path": {
                        "shape": "LineString",
                        "points": [
                            {
                                "coord": [
                                    121.68608278233754,
                                    38.81451030153296
                                ],
                                "spd": 9.000076976906637
                            }
                        ]
                    }
                },
                {
                    "id": "a6",
                    "path": {
                        "shape": "LineString",
                        "points": [
                            {
                                "coord": [
                                    121.67967689957855,
                                    38.81105236664077
                                ],
                                "spd": 9.000076976907105
                            }
                        ]
                    }
                },
                {
                    "id": "a7",
                    "path": {
                        "shape": "LineString",
                        "points": [
                            {
                                "coord": [
                                    121.6717353559328,
                                    38.80944687210242
                                ],
                                "spd": 0.0
                            }
                        ]
                    }
                },
                {
                    "id": "a8",
                    "path": {
                        "shape": "LineString",
                        "points": [
                            {
                                "coord": [
                                    121.68264256220472,
                                    38.803609465137754
                                ],
                                "spd": 20.000171059792958
                            }
                        ]
                    }
                },
                {
                    "id": "a1",
                    "path": {
                        "shape": "LineString",
                        "points": [
                            {
                                "coord": [
                                    121.68737506505946,
                                    38.82849972627012
                                ],
                                "spd": 9.000076976907332
                            }
                        ]
                    }
                },
                {
                    "id": "a2",
                    "path": {
                        "shape": "LineString",
                        "points": [
                            {
                                "coord": [
                                    121.68713695744593,
                                    38.82397244143634
                                ],
                                "spd": 9.000076976906529
                            }
                        ]
                    }
                },
                {
                    "id": "a3",
                    "path": {
                        "shape": "LineString",
                        "points": [
                            {
                                "coord": [
                                    121.68814169761252,
                                    38.817252488164584
                                ],
                                "spd": 20.000171059793427
                            }
                        ]
                    }
                },
                {
                    "id": "a4",
                    "path": {
                        "shape": "LineString",
                        "points": [
                            {
                                "coord": [
                                    121.68479163708531,
                                    38.82158321082087
                                ],
                                "spd": 20.00017105979263
                            }
                        ]
                    }
                },
                {
                    "id": "a5",
                    "path": {
                        "shape": "LineString",
                        "points": [
                            {
                                "coord": [
                                    121.68608278233754,
                                    38.81451030153296
                                ],
                                "spd": 9.000076976906637
                            }
                        ]
                    }
                },
                {
                    "id": "a6",
                    "path": {
                        "shape": "LineString",
                        "points": [
                            {
                                "coord": [
                                    121.67967689957855,
                                    38.81105236664077
                                ],
                                "spd": 9.000076976907105
                            }
                        ]
                    }
                },
                {
                    "id": "a7",
                    "path": {
                        "shape": "LineString",
                        "points": [
                            {
                                "coord": [
                                    121.6717353559328,
                                    38.80944687210242
                                ],
                                "spd": 0.0
                            }
                        ]
                    }
                },
                {
                    "id": "a8",
                    "path": {
                        "shape": "LineString",
                        "points": [
                            {
                                "coord": [
                                    121.68264256220472,
                                    38.803609465137754
                                ],
                                "spd": 20.000171059792958
                            }
                        ]
                    }
                },
                {
                    "id": "a1",
                    "path": {
                        "shape": "LineString",
                        "points": [
                            {
                                "coord": [
                                    121.68737506505946,
                                    38.82849972627012
                                ],
                                "spd": 9.000076976907332
                            }
                        ]
                    }
                },
                {
                    "id": "a2",
                    "path": {
                        "shape": "LineString",
                        "points": [
                            {
                                "coord": [
                                    121.68713695744593,
                                    38.82397244143634
                                ],
                                "spd": 9.000076976906529
                            }
                        ]
                    }
                },
                {
                    "id": "a3",
                    "path": {
                        "shape": "LineString",
                        "points": [
                            {
                                "coord": [
                                    121.68814169761252,
                                    38.817252488164584
                                ],
                                "spd": 20.000171059793427
                            }
                        ]
                    }
                },
                {
                    "id": "a4",
                    "path": {
                        "shape": "LineString",
                        "points": [
                            {
                                "coord": [
                                    121.68479163708531,
                                    38.82158321082087
                                ],
                                "spd": 20.00017105979263
                            }
                        ]
                    }
                },
                {
                    "id": "a5",
                    "path": {
                        "shape": "LineString",
                        "points": [
                            {
                                "coord": [
                                    121.68608278233754,
                                    38.81451030153296
                                ],
                                "spd": 9.000076976906637
                            }
                        ]
                    }
                },
                {
                    "id": "a6",
                    "path": {
                        "shape": "LineString",
                        "points": [
                            {
                                "coord": [
                                    121.67967689957855,
                                    38.81105236664077
                                ],
                                "spd": 9.000076976907105
                            }
                        ]
                    }
                },
                {
                    "id": "a7",
                    "path": {
                        "shape": "LineString",
                        "points": [
                            {
                                "coord": [
                                    121.6717353559328,
                                    38.80944687210242
                                ],
                                "spd": 0.0
                            }
                        ]
                    }
                },
                {
                    "id": "a8",
                    "path": {
                        "shape": "LineString",
                        "points": [
                            {
                                "coord": [
                                    121.68264256220472,
                                    38.803609465137754
                                ],
                                "spd": 20.000171059792958
                            }
                        ]
                    }
                },
                {
                    "id": "a1",
                    "path": {
                        "shape": "LineString",
                        "points": [
                            {
                                "coord": [
                                    121.68737506505946,
                                    38.82849972627012
                                ],
                                "spd": 9.000076976907332
                            }
                        ]
                    }
                },
                {
                    "id": "a2",
                    "path": {
                        "shape": "LineString",
                        "points": [
                            {
                                "coord": [
                                    121.68713695744593,
                                    38.82397244143634
                                ],
                                "spd": 9.000076976906529
                            }
                        ]
                    }
                },
                {
                    "id": "a3",
                    "path": {
                        "shape": "LineString",
                        "points": [
                            {
                                "coord": [
                                    121.68814169761252,
                                    38.817252488164584
                                ],
                                "spd": 20.000171059793427
                            }
                        ]
                    }
                },
                {
                    "id": "a4",
                    "path": {
                        "shape": "LineString",
                        "points": [
                            {
                                "coord": [
                                    121.68479163708531,
                                    38.82158321082087
                                ],
                                "spd": 20.00017105979263
                            }
                        ]
                    }
                },
                {
                    "id": "a5",
                    "path": {
                        "shape": "LineString",
                        "points": [
                            {
                                "coord": [
                                    121.68608278233754,
                                    38.81451030153296
                                ],
                                "spd": 9.000076976906637
                            }
                        ]
                    }
                },
                {
                    "id": "a6",
                    "path": {
                        "shape": "LineString",
                        "points": [
                            {
                                "coord": [
                                    121.67967689957855,
                                    38.81105236664077
                                ],
                                "spd": 9.000076976907105
                            }
                        ]
                    }
                },
                {
                    "id": "a7",
                    "path": {
                        "shape": "LineString",
                        "points": [
                            {
                                "coord": [
                                    121.6717353559328,
                                    38.80944687210242
                                ],
                                "spd": 0.0
                            }
                        ]
                    }
                },
                {
                    "id": "a8",
                    "path": {
                        "shape": "LineString",
                        "points": [
                            {
                                "coord": [
                                    121.68264256220472,
                                    38.803609465137754
                                ],
                                "spd": 20.000171059792958
                            }
                        ]
                    }
                },
                {
                    "id": "a1",
                    "path": {
                        "shape": "LineString",
                        "points": [
                            {
                                "coord": [
                                    121.68737506505946,
                                    38.82849972627012
                                ],
                                "spd": 9.000076976907332
                            }
                        ]
                    }
                },
                {
                    "id": "a2",
                    "path": {
                        "shape": "LineString",
                        "points": [
                            {
                                "coord": [
                                    121.68713695744593,
                                    38.82397244143634
                                ],
                                "spd": 9.000076976906529
                            }
                        ]
                    }
                },
                {
                    "id": "a3",
                    "path": {
                        "shape": "LineString",
                        "points": [
                            {
                                "coord": [
                                    121.68814169761252,
                                    38.817252488164584
                                ],
                                "spd": 20.000171059793427
                            }
                        ]
                    }
                },
                {
                    "id": "a4",
                    "path": {
                        "shape": "LineString",
                        "points": [
                            {
                                "coord": [
                                    121.68479163708531,
                                    38.82158321082087
                                ],
                                "spd": 20.00017105979263
                            }
                        ]
                    }
                },
                {
                    "id": "a5",
                    "path": {
                        "shape": "LineString",
                        "points": [
                            {
                                "coord": [
                                    121.68608278233754,
                                    38.81451030153296
                                ],
                                "spd": 9.000076976906637
                            }
                        ]
                    }
                },
                {
                    "id": "a6",
                    "path": {
                        "shape": "LineString",
                        "points": [
                            {
                                "coord": [
                                    121.67967689957855,
                                    38.81105236664077
                                ],
                                "spd": 9.000076976907105
                            }
                        ]
                    }
                },
                {
                    "id": "a7",
                    "path": {
                        "shape": "LineString",
                        "points": [
                            {
                                "coord": [
                                    121.6717353559328,
                                    38.80944687210242
                                ],
                                "spd": 0.0
                            }
                        ]
                    }
                },
                {
                    "id": "a8",
                    "path": {
                        "shape": "LineString",
                        "points": [
                            {
                                "coord": [
                                    121.68264256220472,
                                    38.803609465137754
                                ],
                                "spd": 20.000171059792958
                            }
                        ]
                    }
                }
            ]
        }
    }
}