{
    "id": 2,
    "method": "stage_2",
    "content": {
        "arguments": {
            "vesPostion": {
                "a1": {
                    "coord": [
                        121.69696173107195,
                        38.82868408278701
                    ],
                    "spd": 20.000171059792855,
                    "course": 290.3484657490674
                },
                "a2": {
                    "coord": [
                        121.69532328631652,
                        38.82219357410827
                    ],
                    "spd": 20.000171059792855,
                    "course": 290.3484657490674
                },
                "a3": {
                    "coord": [
                        121.69460078363097,
                        38.817939453337154
                    ],
                    "spd": 20.000171059792855,
                    "course": 290.3484657490674
                },
                "a4": {
                    "coord": [
                        121.69725170270257,
                        38.82350565789398
                    ],
                    "spd": 20.000171059792855,
                    "course": 290.3484657490674
                },
                "a5": {
                    "coord": [
                        121.69949070905959,
                        38.81442265911626
                    ],
                    "spd": 20.000171059792855,
                    "course": 290.3484657490674
                },
                "a6": {
                    "coord": [
                        121.69615355540431,
                        38.81167417246786
                    ],
                    "spd": 20.000171059792855,
                    "course": 290.3484657490674
                },
                "a7": {
                    "coord": [
                        121.69002953281415,
                        38.80781590973194
                    ],
                    "spd": 20.000171059792855,
                    "course": 290.3484657490674
                },
                "a8": {
                    "coord": [
                        121.68933322089842,
                        38.80207051199039
                    ],
                    "spd": 20.000171059792855,
                    "course": 290.3484657490674
                }
            },
            "road": [
                {
                    "id": "a1",
                    "path": {
                        "shape": "LineString",
                        "points": [
                            {
                                "coord": [
                                    121.69731563363368,
                                    38.82870087189603
                                ],
                                "spd": 20.000171059793594
                            }
                        ]
                    }
                },
                {
                    "id": "a2",
                    "path": {
                        "shape": "LineString",
                        "points": [
                            {
                                "coord": [
                                    121.69564302300985,
                                    38.82211739581021
                                ],
                                "spd": 20.00017105979296
                            }
                        ]
                    }
                },
                {
                    "id": "a3",
                    "path": {
                        "shape": "LineString",
                        "points": [
                            {
                                "coord": [
                                    121.69461780074144,
                                    38.818017442205615
                                ],
                                "spd": 9.000076976906925
                            }
                        ]
                    }
                },
                {
                    "id": "a4",
                    "path": {
                        "shape": "LineString",
                        "points": [
                            {
                                "coord": [
                                    121.69733861686957,
                                    38.82343979463896
                                ],
                                "spd": 9.000076976906922
                            }
                        ]
                    }
                },
                {
                    "id": "a5",
                    "path": {
                        "shape": "LineString",
                        "points": [
                            {
                                "coord": [
                                    121.69932382269228,
                                    38.81437604883623
                                ],
                                "spd": 20.000171059793175
                            }
                        ]
                    }
                },
                {
                    "id": "a6",
                    "path": {
                        "shape": "LineString",
                        "points": [
                            {
                                "coord": [
                                    121.69599539856459,
                                    38.81166261744174
                                ],
                                "spd": 9.000076976906733
                            }
                        ]
                    }
                },
                {
                    "id": "a7",
                    "path": {
                        "shape": "LineString",
                        "points": [
                            {
                                "coord": [
                                    121.69037908238717,
                                    38.8077847180782
                                ],
                                "spd": 20.000171059792898
                            }
                        ]
                    }
                },
                {
                    "id": "a8",
                    "path": {
                        "shape": "LineString",
                        "points": [
                            {
                                "coord": [
                                    121.68955172892582,
                                    38.80193318721795
                                ],
                                "spd": 20.00017105979347
                            }
                        ]
                    }
                },
                {
                    "id": "a1",
                    "path": {
                        "shape": "LineString",
                        "points": [
                            {
                                "coord": [
                                    121.69731563363368,
                                    38.82870087189603
                                ],
                                "spd": 20.000171059793594
                            }
                        ]
                    }
                },
                {
                    "id": "a2",
                    "path": {
                        "shape": "LineString",
                        "points": [
                            {
                                "coord": [
                                    121.69564302300985,
                                    38.82211739581021
                                ],
                                "spd": 20.00017105979296
                            }
                        ]
                    }
                },
                {
                    "id": "a3",
                    "path": {
                        "shape": "LineString",
                        "points": [
                            {
                                "coord": [
                                    121.69461780074144,
                                    38.818017442205615
                                ],
                                "spd": 9.000076976906925
                            }
                        ]
                    }
                },
                {
                    "id": "a4",
                    "path": {
                        "shape": "LineString",
                        "points": [
                            {
                                "coord": [
                                    121.69733861686957,
                                    38.82343979463896
                                ],
                                "spd": 9.000076976906922
                            }
                        ]
                    }
                },
                {
                    "id": "a5",
                    "path": {
                        "shape": "LineString",
                        "points": [
                            {
                                "coord": [
                                    121.69932382269228,
                                    38.81437604883623
                                ],
                                "spd": 20.000171059793175
                            }
                        ]
                    }
                },
                {
                    "id": "a6",
                    "path": {
                        "shape": "LineString",
                        "points": [
                            {
                                "coord": [
                                    121.69599539856459,
                                    38.81166261744174
                                ],
                                "spd": 9.000076976906733
                            }
                        ]
                    }
                },
                {
                    "id": "a7",
                    "path": {
                        "shape": "LineString",
                        "points": [
                            {
                                "coord": [
                                    121.69037908238717,
                                    38.8077847180782
                                ],
                                "spd": 20.000171059792898
                            }
                        ]
                    }
                },
                {
                    "id": "a8",
                    "path": {
                        "shape": "LineString",
                        "points": [
                            {
                                "coord": [
                                    121.68955172892582,
                                    38.80193318721795
                                ],
                                "spd": 20.00017105979347
                            }
                        ]
                    }
                },
                {
                    "id": "a1",
                    "path": {
                        "shape": "LineString",
                        "points": [
                            {
                                "coord": [
                                    121.69731563363368,
                                    38.82870087189603
                                ],
                                "spd": 20.000171059793594
                            }
                        ]
                    }
                },
                {
                    "id": "a2",
                    "path": {
                        "shape": "LineString",
                        "points": [
                            {
                                "coord": [
                                    121.69564302300985,
                                    38.82211739581021
                                ],
                                "spd": 20.00017105979296
                            }
                        ]
                    }
                },
                {
                    "id": "a3",
                    "path": {
                        "shape": "LineString",
                        "points": [
                            {
                                "coord": [
                                    121.69461780074144,
                                    38.818017442205615
                                ],
                                "spd": 9.000076976906925
                            }
                        ]
                    }
                },
                {
                    "id": "a4",
                    "path": {
                        "shape": "LineString",
                        "points": [
                            {
                                "coord": [
                                    121.69733861686957,
                                    38.82343979463896
                                ],
                                "spd": 9.000076976906922
                            }
                        ]
                    }
                },
                {
                    "id": "a5",
                    "path": {
                        "shape": "LineString",
                        "points": [
                            {
                                "coord": [
                                    121.69932382269228,
                                    38.81437604883623
                                ],
                                "spd": 20.000171059793175
                            }
                        ]
                    }
                },
                {
                    "id": "a6",
                    "path": {
                        "shape": "LineString",
                        "points": [
                            {
                                "coord": [
                                    121.69599539856459,
                                    38.81166261744174
                                ],
                                "spd": 9.000076976906733
                            }
                        ]
                    }
                },
                {
                    "id": "a7",
                    "path": {
                        "shape": "LineString",
                        "points": [
                            {
                                "coord": [
                                    121.69037908238717,
                                    38.8077847180782
                                ],
                                "spd": 20.000171059792898
                            }
                        ]
                    }
                },
                {
                    "id": "a8",
                    "path": {
                        "shape": "LineString",
                        "points": [
                            {
                                "coord": [
                                    121.68955172892582,
                                    38.80193318721795
                                ],
                                "spd": 20.00017105979347
                            }
                        ]
                    }
                },
                {
                    "id": "a1",
                    "path": {
                        "shape": "LineString",
                        "points": [
                            {
                                "coord": [
                                    121.69731563363368,
                                    38.82870087189603
                                ],
                                "spd": 20.000171059793594
                            }
                        ]
                    }
                },
                {
                    "id": "a2",
                    "path": {
                        "shape": "LineString",
                        "points": [
                            {
                                "coord": [
                                    121.69564302300985,
                                    38.82211739581021
                                ],
                                "spd": 20.00017105979296
                            }
                        ]
                    }
                },
                {
                    "id": "a3",
                    "path": {
                        "shape": "LineString",
                        "points": [
                            {
                                "coord": [
                                    121.69461780074144,
                                    38.818017442205615
                                ],
                                "spd": 9.000076976906925
                            }
                        ]
                    }
                },
                {
                    "id": "a4",
                    "path": {
                        "shape": "LineString",
                        "points": [
                            {
                                "coord": [
                                    121.69733861686957,
                                    38.82343979463896
                                ],
                                "spd": 9.000076976906922
                            }
                        ]
                    }
                },
                {
                    "id": "a5",
                    "path": {
                        "shape": "LineString",
                        "points": [
                            {
                                "coord": [
                                    121.69932382269228,
                                    38.81437604883623
                                ],
                                "spd": 20.000171059793175
                            }
                        ]
                    }
                },
                {
                    "id": "a6",
                    "path": {
                        "shape": "LineString",
                        "points": [
                            {
                                "coord": [
                                    121.69599539856459,
                                    38.81166261744174
                                ],
                                "spd": 9.000076976906733
                            }
                        ]
                    }
                },
                {
                    "id": "a7",
                    "path": {
                        "shape": "LineString",
                        "points": [
                            {
                                "coord": [
                                    121.69037908238717,
                                    38.8077847180782
                                ],
                                "spd": 20.000171059792898
                            }
                        ]
                    }
                },
                {
                    "id": "a8",
                    "path": {
                        "shape": "LineString",
                        "points": [
                            {
                                "coord": [
                                    121.68955172892582,
                                    38.80193318721795
                                ],
                                "spd": 20.00017105979347
                            }
                        ]
                    }
                },
                {
                    "id": "a1",
                    "path": {
                        "shape": "LineString",
                        "points": [
                            {
                                "coord": [
                                    121.69731563363368,
                                    38.82870087189603
                                ],
                                "spd": 20.000171059793594
                            }
                        ]
                    }
                },
                {
                    "id": "a2",
                    "path": {
                        "shape": "LineString",
                        "points": [
                            {
                                "coord": [
                                    121.69564302300985,
                                    38.82211739581021
                                ],
                                "spd": 20.00017105979296
                            }
                        ]
                    }
                },
                {
                    "id": "a3",
                    "path": {
                        "shape": "LineString",
                        "points": [
                            {
                                "coord": [
                                    121.69461780074144,
                                    38.818017442205615
                                ],
                                "spd": 9.000076976906925
                            }
                        ]
                    }
                },
                {
                    "id": "a4",
                    "path": {
                        "shape": "LineString",
                        "points": [
                            {
                                "coord": [
                                    121.69733861686957,
                                    38.82343979463896
                                ],
                                "spd": 9.000076976906922
                            }
                        ]
                    }
                },
                {
                    "id": "a5",
                    "path": {
                        "shape": "LineString",
                        "points": [
                            {
                                "coord": [
                                    121.69932382269228,
                                    38.81437604883623
                                ],
                                "spd": 20.000171059793175
                            }
                        ]
                    }
                },
                {
                    "id": "a6",
                    "path": {
                        "shape": "LineString",
                        "points": [
                            {
                                "coord": [
                                    121.69599539856459,
                                    38.81166261744174
                                ],
                                "spd": 9.000076976906733
                            }
                        ]
                    }
                },
                {
                    "id": "a7",
                    "path": {
                        "shape": "LineString",
                        "points": [
                            {
                                "coord": [
                                    121.69037908238717,
                                    38.8077847180782
                                ],
                                "spd": 20.000171059792898
                            }
                        ]
                    }
                },
                {
                    "id": "a8",
                    "path": {
                        "shape": "LineString",
                        "points": [
                            {
                                "coord": [
                                    121.68955172892582,
                                    38.80193318721795
                                ],
                                "spd": 20.00017105979347
                            }
                        ]
                    }
                },
                {
                    "id": "a1",
                    "path": {
                        "shape": "LineString",
                        "points": [
                            {
                                "coord": [
                                    121.69731563363368,
                                    38.82870087189603
                                ],
                                "spd": 20.000171059793594
                            }
                        ]
                    }
                },
                {
                    "id": "a2",
                    "path": {
                        "shape": "LineString",
                        "points": [
                            {
                                "coord": [
                                    121.69564302300985,
                                    38.82211739581021
                                ],
                                "spd": 20.00017105979296
                            }
                        ]
                    }
                },
                {
                    "id": "a3",
                    "path": {
                        "shape": "LineString",
                        "points": [
                            {
                                "coord": [
                                    121.69461780074144,
                                    38.818017442205615
                                ],
                                "spd": 9.000076976906925
                            }
                        ]
                    }
                },
                {
                    "id": "a4",
                    "path": {
                        "shape": "LineString",
                        "points": [
                            {
                                "coord": [
                                    121.69733861686957,
                                    38.82343979463896
                                ],
                                "spd": 9.000076976906922
                            }
                        ]
                    }
                },
                {
                    "id": "a5",
                    "path": {
                        "shape": "LineString",
                        "points": [
                            {
                                "coord": [
                                    121.69932382269228,
                                    38.81437604883623
                                ],
                                "spd": 20.000171059793175
                            }
                        ]
                    }
                },
                {
                    "id": "a6",
                    "path": {
                        "shape": "LineString",
                        "points": [
                            {
                                "coord": [
                                    121.69599539856459,
                                    38.81166261744174
                                ],
                                "spd": 9.000076976906733
                            }
                        ]
                    }
                },
                {
                    "id": "a7",
                    "path": {
                        "shape": "LineString",
                        "points": [
                            {
                                "coord": [
                                    121.69037908238717,
                                    38.8077847180782
                                ],
                                "spd": 20.000171059792898
                            }
                        ]
                    }
                },
                {
                    "id": "a8",
                    "path": {
                        "shape": "LineString",
                        "points": [
                            {
                                "coord": [
                                    121.68955172892582,
                                    38.80193318721795
                                ],
                                "spd": 20.00017105979347
                            }
                        ]
                    }
                },
                {
                    "id": "a1",
                    "path": {
                        "shape": "LineString",
                        "points": [
                            {
                                "coord": [
                                    121.69731563363368,
                                    38.82870087189603
                                ],
                                "spd": 20.000171059793594
                            }
                        ]
                    }
                },
                {
                    "id": "a2",
                    "path": {
                        "shape": "LineString",
                        "points": [
                            {
                                "coord": [
                                    121.69564302300985,
                                    38.82211739581021
                                ],
                                "spd": 20.00017105979296
                            }
                        ]
                    }
                },
                {
                    "id": "a3",
                    "path": {
                        "shape": "LineString",
                        "points": [
                            {
                                "coord": [
                                    121.69461780074144,
                                    38.818017442205615
                                ],
                                "spd": 9.000076976906925
                            }
                        ]
                    }
                },
                {
                    "id": "a4",
                    "path": {
                        "shape": "LineString",
                        "points": [
                            {
                                "coord": [
                                    121.69733861686957,
                                    38.82343979463896
                                ],
                                "spd": 9.000076976906922
                            }
                        ]
                    }
                },
                {
                    "id": "a5",
                    "path": {
                        "shape": "LineString",
                        "points": [
                            {
                                "coord": [
                                    121.69932382269228,
                                    38.81437604883623
                                ],
                                "spd": 20.000171059793175
                            }
                        ]
                    }
                },
                {
                    "id": "a6",
                    "path": {
                        "shape": "LineString",
                        "points": [
                            {
                                "coord": [
                                    121.69599539856459,
                                    38.81166261744174
                                ],
                                "spd": 9.000076976906733
                            }
                        ]
                    }
                },
                {
                    "id": "a7",
                    "path": {
                        "shape": "LineString",
                        "points": [
                            {
                                "coord": [
                                    121.69037908238717,
                                    38.8077847180782
                                ],
                                "spd": 20.000171059792898
                            }
                        ]
                    }
                },
                {
                    "id": "a8",
                    "path": {
                        "shape": "LineString",
                        "points": [
                            {
                                "coord": [
                                    121.68955172892582,
                                    38.80193318721795
                                ],
                                "spd": 20.00017105979347
                            }
                        ]
                    }
                },
                {
                    "id": "a1",
                    "path": {
                        "shape": "LineString",
                        "points": [
                            {
                                "coord": [
                                    121.69731563363368,
                                    38.82870087189603
                                ],
                                "spd": 20.000171059793594
                            }
                        ]
                    }
                },
                {
                    "id": "a2",
                    "path": {
                        "shape": "LineString",
                        "points": [
                            {
                                "coord": [
                                    121.69564302300985,
                                    38.82211739581021
                                ],
                                "spd": 20.00017105979296
                            }
                        ]
                    }
                },
                {
                    "id": "a3",
                    "path": {
                        "shape": "LineString",
                        "points": [
                            {
                                "coord": [
                                    121.69461780074144,
                                    38.818017442205615
                                ],
                                "spd": 9.000076976906925
                            }
                        ]
                    }
                },
                {
                    "id": "a4",
                    "path": {
                        "shape": "LineString",
                        "points": [
                            {
                                "coord": [
                                    121.69733861686957,
                                    38.82343979463896
                                ],
                                "spd": 9.000076976906922
                            }
                        ]
                    }
                },
                {
                    "id": "a5",
                    "path": {
                        "shape": "LineString",
                        "points": [
                            {
                                "coord": [
                                    121.69932382269228,
                                    38.81437604883623
                                ],
                                "spd": 20.000171059793175
                            }
                        ]
                    }
                },
                {
                    "id": "a6",
                    "path": {
                        "shape": "LineString",
                        "points": [
                            {
                                "coord": [
                                    121.69599539856459,
                                    38.81166261744174
                                ],
                                "spd": 9.000076976906733
                            }
                        ]
                    }
                },
                {
                    "id": "a7",
                    "path": {
                        "shape": "LineString",
                        "points": [
                            {
                                "coord": [
                                    121.69037908238717,
                                    38.8077847180782
                                ],
                                "spd": 20.000171059792898
                            }
                        ]
                    }
                },
                {
                    "id": "a8",
                    "path": {
                        "shape": "LineString",
                        "points": [
                            {
                                "coord": [
                                    121.68955172892582,
                                    38.80193318721795
                                ],
                                "spd": 20.00017105979347
                            }
                        ]
                    }
                }
            ]
        }
    }
}