{
  "id": 2,
  "method": "stage_2",
  "content": {
    "arguments": {
      "vesPostion": {
        "a1": {
          "coord": [
            121.67046570818464,
            38.831019461604832
          ],
          "spd": 20.000171059793303,
          "course": 240.36989253986476
        },
        "a2": {
          "coord": [
            121.67049138772877,
            38.825144253107943
          ],
          "spd": 20.000171059792546,
          "course": 269.06777021415206
        },
        "a3": {
          "coord": [
            121.66200407297984,
            38.821155392968024
          ],
          "spd": 20.000171059794038,
          "course": 271.46656178411433
        },
        "a4": {
          "coord": [
            121.66129516065507,
            38.818990164638059
          ],
          "spd": 20.000171059793932,
          "course": 231.14432151931754
        },
        "a5": {
          "coord": [
            121.66334876950728,
            38.815339027701604
          ],
          "spd": 20.000171059793509,
          "course": 175.23768659189352
        },
        "a6": {
          "coord": [
            121.67135669290369,
            38.809376365100427
          ],
          "spd": 9.00007697690767,
          "course": 333.41226885739354
        },
        "a7": {
          "coord": [
            121.66459963184717,
            38.8070648455907
          ],
          "spd": 9.00007697690638,
          "course": 295.50441934813836
        },
        "a8": {
          "coord": [
            121.66268387056871,
            38.803999818848638
          ],
          "spd": 9.0000769769069144,
          "course": 56.063200473851147
        }
      },
      "road": [
        {
          "id": "a1",
          "path": {
            "shape": "LineString",
            "points": {
              "coord": [
                121.67082106645962,
                38.831013251959646
              ],
              "spd": 20.000171059793303
            }
          }
        },
        {
          "id": "a2",
          "path": {
            "shape": "LineString",
            "points": {
              "coord": [
                121.67079695109956,
                38.825055138632223
              ],
              "spd": 20.000171059792546
            }
          }
        },
        {
          "id": "a3",
          "path": {
            "shape": "LineString",
            "points": {
              "coord": [
                121.66230174980467,
                38.821060122455073
              ],
              "spd": 20.000171059794038
            }
          }
        },
        {
          "id": "a4",
          "path": {
            "shape": "LineString",
            "points": {
              "coord": [
                121.66164779421298,
                38.819011993447674
              ],
              "spd": 20.000171059793932
            }
          }
        },
        {
          "id": "a5",
          "path": {
            "shape": "LineString",
            "points": {
              "coord": [
                121.66350956482292,
                38.815494447462008
              ],
              "spd": 20.000171059793509
            }
          }
        },
        {
          "id": "a6",
          "path": {
            "shape": "LineString",
            "points": {
              "coord": [
                121.67134252519224,
                38.809298268710329
              ],
              "spd": 9.00007697690767
            }
          }
        },
        {
          "id": "a7",
          "path": {
            "shape": "LineString",
            "points": {
              "coord": [
                121.66468631062823,
                38.806998970643221
              ],
              "spd": 9.00007697690638
            }
          }
        },
        {
          "id": "a8",
          "path": {
            "shape": "LineString",
            "points": {
              "coord": [
                121.6625241375784,
                38.803996708324817
              ],
              "spd": 9.0000769769069144
            }
          }
        }
      ]
    }
  }
}