{
  "id": 2,
  "method": "stage_2",
  "content": {
    "arguments": {
      "vesPostion": {
        "a1": {
          "coord": [
            121.68574597184205,
            38.830751472289066
          ],
          "spd": 9.00007697690759,
          "course": 109.92944537299934
        },
        "a2": {
          "coord": [
            121.67804629724698,
            38.824170667765365
          ],
          "spd": 20.000171059793335,
          "course": 240.92434834908315
        },
        "a3": {
          "coord": [
            121.68227270034158,
            38.817292906976753
          ],
          "spd": 20.000171059793466,
          "course": 220.86361607123237
        },
        "a4": {
          "coord": [
            121.67872426861976,
            38.820358149032742
          ],
          "spd": 9.00007697690707,
          "course": 109.09178774469164
        },
        "a5": {
          "coord": [
            121.6732429650033,
            38.816233047426124
          ],
          "spd": 20.000171059793537,
          "course": 247.39881813145047
        },
        "a6": {
          "coord": [
            121.67880672316016,
            38.811578205275183
          ],
          "spd": 9.0000769769069251,
          "course": 254.13561390169261
        },
        "a7": {
          "coord": [
            121.68138999813196,
            38.8070025568095
          ],
          "spd": 9.0000769769069819,
          "course": 254.91335477812814
        },
        "a8": {
          "coord": [
            121.67071294744483,
            38.801589892091073
          ],
          "spd": 9.0000769769067581,
          "course": 325.35020822217945
        }
      },
      "road": [
        {
          "id": "a1",
          "path": {
            "shape": "LineString",
            "points": {
              "coord": [
                121.68579818421395,
                38.8307903972298
              ],
              "spd": 9.00007697690759
            }
          }
        },
        {
          "id": "a2",
          "path": {
            "shape": "LineString",
            "points": {
              "coord": [
                121.67840142765242,
                38.824162751154979
              ],
              "spd": 20.000171059793335
            }
          }
        },
        {
          "id": "a3",
          "path": {
            "shape": "LineString",
            "points": {
              "coord": [
                121.6826117471292,
                38.817345184254179
              ],
              "spd": 20.000171059793466
            }
          }
        },
        {
          "id": "a4",
          "path": {
            "shape": "LineString",
            "points": {
              "coord": [
                121.67862311026353,
                38.820418911860607
              ],
              "spd": 9.00007697690736
            }
          }
        },
        {
          "id": "a5",
          "path": {
            "shape": "LineString",
            "points": {
              "coord": [
                121.67359391566319,
                38.81620556628318
              ],
              "spd": 20.000171059793537
            }
          }
        },
        {
          "id": "a6",
          "path": {
            "shape": "LineString",
            "points": {
              "coord": [
                121.67896057269495,
                38.811556836048318
              ],
              "spd": 9.0000769769069251
            }
          }
        },
        {
          "id": "a7",
          "path": {
            "shape": "LineString",
            "points": {
              "coord": [
                121.68154321497393,
                38.806980166532334
              ],
              "spd": 9.000076976907442
            }
          }
        },
        {
          "id": "a8",
          "path": {
            "shape": "LineString",
            "points": {
              "coord": [
                121.67072125478597,
                38.801511619603723
              ],
              "spd": 9.0000769769067581
            }
          }
        }
      ]
    }
  }
}